mda_xdrlib/__init__.py
mda_xdrlib/_version.py
mda_xdrlib/xdrlib.py
mda_xdrlib/tests/__init__.py
mda_xdrlib/tests/test_xdrlib.py
mda_xdrlib-0.2.0.dist-info/LICENSE
mda_xdrlib-0.2.0.dist-info/METADATA
mda_xdrlib-0.2.0.dist-info/WHEEL
mda_xdrlib-0.2.0.dist-info/top_level.txt
mda_xdrlib-0.2.0.dist-info/RECORD
