Metadata-Version: 2.1
Name: mda_xdrlib
Version: 0.2.0
Summary: Stand-alone XDRLIB module (from cpython 3.10.8)
Author-email: The MDAnalysis development team <mdanalysis@numfocus.org>
Maintainer-email: The MDAnalysis development team <mdanalysis@numfocus.org>
License: MDA-XDRLIB LICENSING
Project-URL: Homepage, https://github.com/MDAnalysis/mda-xdrlib
Classifier: Development Status :: 6 - Mature
Classifier: Intended Audience :: Developers
Classifier: Topic :: Software Development :: Libraries :: Python Modules
Classifier: Topic :: System :: Archiving
Classifier: License :: OSI Approved :: Python Software Foundation License
Classifier: Programming Language :: Python :: 3.7
Classifier: Programming Language :: Python :: 3.8
Classifier: Programming Language :: Python :: 3.9
Classifier: Programming Language :: Python :: 3.10
Classifier: Programming Language :: Python :: 3.11
Classifier: Operating System :: OS Independent
Requires-Python: >=3.7
Provides-Extra: testing
License-File: LICENSE
